mypythonlib/__init__.py
mypythonlib/myfunctions.py
mypythonlibzly0323-0.1.0.dist-info/METADATA
mypythonlibzly0323-0.1.0.dist-info/WHEEL
mypythonlibzly0323-0.1.0.dist-info/top_level.txt
mypythonlibzly0323-0.1.0.dist-info/RECORD
